django_mediastream-0.2.1.dist-info/DESCRIPTION.rst
django_mediastream-0.2.1.dist-info/METADATA
django_mediastream-0.2.1.dist-info/RECORD
django_mediastream-0.2.1.dist-info/WHEEL
django_mediastream-0.2.1.dist-info/metadata.json
django_mediastream-0.2.1.dist-info/top_level.txt
example/simpleapp/__init__.py
example/simpleapp/admin.py
example/simpleapp/models.py
example/simpleapp/urls.py
mediastream/__init__.py
mediastream/admin.py
mediastream/apps.py
mediastream/models.py
mediastream/settings.py
mediastream/tasks.py
mediastream/tests.py
mediastream/urls.py
mediastream/utils.py
mediastream/views.py
mediastream/aggregators/__init__.py
mediastream/aggregators/flickr.py
mediastream/aggregators/inaturalist.py
mediastream/aggregators/instagram.py
mediastream/aggregators/ispot.py
mediastream/aggregators/kidsmyshot.py
mediastream/aggregators/projectnoah.py
mediastream/aggregators/twitter.py
mediastream/aggregators/yourshot.py
mediastream/migrations/0001_initial.py
mediastream/migrations/0002_rename_referesh_rate.py
mediastream/migrations/__init__.py
