Metadata-Version: 2.0
Name: django-mediastream
Version: 0.2.1
Summary: mediastream
Home-page: https://github.com/Natgeoed/django-mediastream
Author: Corey Oordt
Author-email: coreyoordt@gmail.com
License: UNKNOWN
Platform: UNKNOWN
Classifier: Framework :: Django
Requires-Dist: djorm-ngs-pgarray (==1.2.4)
Requires-Dist: flickrapi (==2.1.2)
